{
	"description": "项目配置文件。",
	"setting": {
		"urlCheck": false,
		"es6": true,
		"postcss": true,
		"minified": true,
		"newFeature": true,
		"coverView": true,
		"autoAudits": false,
		"checkInvalidKey": true,
		"checkSiteMap": true,
		"uploadWithSourceMap": true,
		"babelSetting": {
			"ignore": [],
			"disablePlugins": [],
			"outputPath": ""
		}
	},
	"compileType": "miniprogram",
	"libVersion": "2.8.1",
	"appid": "wx1e04804aea8b960e",
	"projectname": "%E6%94%BE%E7%96%97%E4%BA%91",
	"isGameTourist": false,
	"simulatorType": "wechat",
	"simulatorPluginLibVersion": {},
	"condition": {
		"search": {
			"current": -1,
			"list": []
		},
		"conversation": {
			"current": -1,
			"list": []
		},
		"plugin": {
			"current": -1,
			"list": []
		},
		"game": {
			"currentL": -1,
			"list": []
		},
		"miniprogram": {
			"current": 1,
			"list": [
				{
					"id": 0,
					"name": "管理员",
					"pathName": "pages/admin/admin",
					"query": "",
					"scene": 1011
				},
				{
					"id": -1,
					"name": "二维码测试",
					"pathName": "pages/login/login",
					"query": "admin=true",
					"scene": 1011
				}
			]
		}
	}
}